balderhub/fileops/__init__.py
balderhub/fileops/_version.py
balderhub/fileops/lib/__init__.py
balderhub/fileops/lib/scenario_features/__init__.py
balderhub/fileops/lib/scenario_features/directory_copyer_feature.py
balderhub/fileops/lib/scenario_features/directory_creator_feature.py
balderhub/fileops/lib/scenario_features/directory_deleter_feature.py
balderhub/fileops/lib/scenario_features/directory_mover_feature.py
balderhub/fileops/lib/scenario_features/directory_renamer_feature.py
balderhub/fileops/lib/scenario_features/file_system_navigator_feature.py
balderhub/fileops/lib/setup_features/__init__.py
balderhub/fileops/lib/utils/__init__.py
balderhub/fileops/lib/utils/directory_item.py
balderhub/fileops/lib/utils/file_item.py
balderhub/fileops/lib/utils/file_system_item.py
balderhub/fileops/lib/utils/file_system_item_list.py
balderhub/fileops/scenarios/__init__.py
balderhub/fileops/scenarios/abstract_scenario_base.py
balderhub/fileops/scenarios/scenario_dir_copy.py
balderhub/fileops/scenarios/scenario_dir_create.py
balderhub/fileops/scenarios/scenario_dir_delete.py
balderhub/fileops/scenarios/scenario_dir_move.py
balderhub/fileops/scenarios/scenario_dir_rename.py
balderhub/fileops/setups/__init__.py
balderhub_fileops-0.0.1b0.dist-info/licenses/LICENSE
balderhub_fileops-0.0.1b0.dist-info/METADATA
balderhub_fileops-0.0.1b0.dist-info/WHEEL
balderhub_fileops-0.0.1b0.dist-info/top_level.txt
balderhub_fileops-0.0.1b0.dist-info/RECORD
