Metadata-Version: 2.4
Name: balderhub-fileops
Version: 0.0.1b0
Summary: balderhub-fileops: BalderHub Project that provides features and scenarios to test file operations
Home-page: https://hub.balder.dev/projects/fileops
Author: Max Stahlschmidt and others
License: MIT
Project-URL: Source, https://github.com/balder-dev/balderhub-fileops/
Project-URL: Tracker, https://github.com/balder-dev/balderhub-fileops/issues
Keywords: test,systemtest,reusable,scenario,junit,balder
Platform: unix
Platform: linux
Platform: osx
Platform: cygwin
Platform: win32
Classifier: License :: OSI Approved :: MIT License
Classifier: Operating System :: MacOS :: MacOS X
Classifier: Operating System :: Microsoft :: Windows
Classifier: Operating System :: POSIX
Classifier: Intended Audience :: Developers
Classifier: Programming Language :: Python :: 3
Classifier: Programming Language :: Python :: 3 :: Only
Classifier: Programming Language :: Python :: 3.9
Classifier: Programming Language :: Python :: 3.10
Classifier: Topic :: Software Development :: Libraries
Classifier: Topic :: Software Development :: Testing
Classifier: Topic :: Utilities
Requires-Python: >=3.9
License-File: LICENSE
Requires-Dist: baldertest
Dynamic: license-file
